Workbook

Sheet despesa_funcao
A1: Ano | B1: Mês | C1: Classificação orçamentária | D1: Secretaria | E1: Função | F1: Subfunção | G1: Natureza da despesa | H1: Fonte de recurso | I1: Empenhado (R$) | J1: Liquidado (R$) | K1: Pago (R$)
A2: 2026 | B2: 2 | C2: 05.10.3.1.90.11.04.122.0001.2.002.01.1100000 | D2: Gabinete do Prefeito | E2: ADMINISTRAÇÃO | F2: ADMINISTRAÇÃO GERAL | G2: VENCIMENTOS E VANTAGENS FIXAS - PESSOAL CIVIL | H2: TESOURO | I2: 67673.06 | J2: 67673.06 | K2: 67673.06
A3: 2026 | B3: 2 | C3: 10.10.3.1.90.11.04.122.0002.2.003.01.1100000 | D3: SECRETARIA DE GOVERNANÇA | E3: ADMINISTRAÇÃO | F3: ADMINISTRAÇÃO GERAL | G3: VENCIMENTOS E VANTAGENS FIXAS - PESSOAL CIVIL | H3: TESOURO | I3: 937110.89 | J3: 937110.89 | K3: 937110.89
A4: 2026 | B4: 2 | C4: 10.10.3.3.50.85.04.122.0002.2.004.01.1100000 | D4: SECRETARIA DE GOVERNANÇA | E4: ADMINISTRAÇÃO | F4: ADMINISTRAÇÃO GERAL | G4: CONTRATO DE GESTÃO- | H4: TESOURO | I4: 0 | J4: 221405.73 | K4: 221405.73
A5: 2026 | B5: 2 | C5: 10.10.3.3.90.14.04.122.0002.2.003.01.1100000 | D5: SECRETARIA DE GOVERNANÇA | E5: ADMINISTRAÇÃO | F5: ADMINISTRAÇÃO GERAL | G5: DIÁRIAS - PESSOAL CIVIL | H5: TESOURO | I5: 540 | J5: 540 | K5: 540
A6: 2026 | B6: 2 | C6: 10.10.3.3.90.30.04.122.0002.2.005.01.1100000 | D6: SECRETARIA DE GOVERNANÇA | E6: ADMINISTRAÇÃO | F6: ADMINISTRAÇÃO GERAL | G6: MATERIAL DE CONSUMO | H6: TESOURO | I6: 47700.8 | J6: 11858.2 | K6: 4684.8
A7: 2026 | B7: 2 | C7: 10.10.3.3.90.30.04.122.0002.2.008.01.1100000 | D7: SECRETARIA DE GOVERNANÇA | E7: ADMINISTRAÇÃO | F7: ADMINISTRAÇÃO GERAL | G7: MATERIAL DE CONSUMO | H7: TESOURO | I7: 20770.78 | J7: 16492.95 | K7: 3140.73
A8: 2026 | B8: 2 | C8: 10.10.3.3.90.30.04.122.0002.2.008.92.1000252 | D8: SECRETARIA DE GOVERNANÇA | E8: ADMINISTRAÇÃO | F8: ADMINISTRAÇÃO GERAL | G8: MATERIAL DE CONSUMO | H8: TRANSFERENCIAS E CONVENIOS ESTADUAIS - VINCULADOS - EXERCÍCIO ANTERIOR | I8: 0 | J8: 1904.48 | K8: 1904.48
A9: 2026 | B9: 2 | C9: 10.10.3.3.90.30.04.122.0002.2.009.01.1100000 | D9: SECRETARIA DE GOVERNANÇA | E9: ADMINISTRAÇÃO | F9: ADMINISTRAÇÃO GERAL | G9: MATERIAL DE CONSUMO | H9: TESOURO | I9: 0 | J9: 133.6 | K9: 0
A10: 2026 | B10: 2 | C10: 10.10.3.3.90.33.04.122.0002.2.003.01.1100000 | D10: SECRETARIA DE GOVERNANÇA | E10: ADMINISTRAÇÃO | F10: ADMINISTRAÇÃO GERAL | G10: PASSAGENS E DESPESAS COM LOCOMOÇÃO | H10: TESOURO | I10: 0 | J10: 24270 | K10: 21650
A11: 2026 | B11: 2 | C11: 10.10.3.3.90.36.04.122.0002.2.003.01.1100000 | D11: SECRETARIA DE GOVERNANÇA | E11: ADMINISTRAÇÃO | F11: ADMINISTRAÇÃO GERAL | G11: OUTROS SERVIÇOS DE TERCEIROS - PESSOA FÍSICA | H11: TESOURO | I11: 15599.65 | J11: 15599.65 | K11: 15599.65
A12: 2026 | B12: 2 | C12: 10.10.3.3.90.39.04.122.0002.2.003.01.1100000 | D12: SECRETARIA DE GOVERNANÇA | E12: ADMINISTRAÇÃO | F12: ADMINISTRAÇÃO GERAL | G12: OUTROS SERVIÇOS DE TERCEIROS - PESSOA JURÍDICA | H12: TESOURO | I12: 12600 | J12: 12600 | K12: 12600
A13: 2026 | B13: 2 | C13: 10.10.3.3.90.39.04.122.0002.2.004.01.1100000 | D13: SECRETARIA DE GOVERNANÇA | E13: ADMINISTRAÇÃO | F13: ADMINISTRAÇÃO GERAL | G13: OUTROS SERVIÇOS DE TERCEIROS - PESSOA JURÍDICA | H13: TESOURO | I13: 414578.83 | J13: 751006.15 | K13: 676190.69
... A444: 2026 | B444: 2 | C444: 90.10.4.4.90.92.16.482.0016.1.012.01.1100000 | D444: SECRETARIA DE HABITAÇÃO E REGULARIZAÇÃO FUNDIÁRIA | E444: HABITAÇÃO | F444: HABITAÇÃO URBANA | G444: DESPESAS DE EXERCÍCIOS ANTERIORES | H444: TESOURO | I444: 0 | J444: 10650.33 | K444: 51920.35

Sheet Planilha2
A1: Rótulos de Linha | B1: Soma de Total de Gastos em Fevereiro/2026
A2: Gabinete do Prefeito | B2: 67673.06
A3: SECRETARIA DE INOVAÇÃO E DESENVOLVIMENTO ECONÔMICO | B3: 474178.15
A4: SECRETARIA DE HABITAÇÃO E REGULARIZAÇÃO FUNDIÁRIA | B4: 924217.23
A5: SECRETARIA DE ASSUNTOS JURÍDICOS | B5: 1182770
A6: SECRETARIA DE URBANISMO E SUSTENTABILIDADE | B6: 1644914.5
A7: SECRETARIA DE GESTÃO DE OBRAS | B7: 2361341.1
A8: SECRETARIA DE GOVERNANÇA | B8: 3049447.7
A9: SECRETARIA DE PROTEÇÃO AO CIDADÃO | B9: 5438913.9
A10: SECRETARIA DE ESPORTE E QUALIDADE DE VIDA | B10: 5975771.6
A11: SECRETARIA DE APOIO SOCIAL AO CIDADÃO | B11: 8654355
A12: SECRETARIA DE GESTÃO ADMINISTRATIVA E FINANÇAS | B12: 8665883.4
A13: SECRETARIA DE MANUTENÇÃO DA CIDADE | B13: 25107844
... A18: Total Geral | B18: 3.1334934e+08

Sheet Planilha1
A1: Secretaria | B1: Total de Gastos em Fevereiro/2026 | C1: Total de Itens pagos
A2: Gabinete do Prefeito | B2: =SUMIF(despesa_funcao!D:D,A2,despesa_funcao!K:K) -> 67673.06 | C2: =COUNTIF(despesa_funcao!D:D,A:A) -> 1
A3: SECRETARIA DE GOVERNANÇA | B3: =SUMIF(despesa_funcao!D:D,A3,despesa_funcao!K:K) -> 3049447.7 | C3: =COUNTIF(despesa_funcao!D:D,A:A) -> 21
A4: SECRETARIA DE ASSUNTOS JURÍDICOS | B4: =SUMIF(despesa_funcao!D:D,A4,despesa_funcao!K:K) -> 1182770 | C4: =COUNTIF(despesa_funcao!D:D,A:A) -> 16
A5: SECRETARIA DE GESTÃO ADMINISTRATIVA E FINANÇAS | B5: =SUMIF(despesa_funcao!D:D,A5,despesa_funcao!K:K) -> 8665883.4 | C5: =COUNTIF(despesa_funcao!D:D,A:A) -> 16
A6: SECRETARIA DE URBANISMO E SUSTENTABILIDADE | B6: =SUMIF(despesa_funcao!D:D,A6,despesa_funcao!K:K) -> 1644914.5 | C6: =COUNTIF(despesa_funcao!D:D,A:A) -> 16
A7: SECRETARIA DE GESTÃO DE OBRAS | B7: =SUMIF(despesa_funcao!D:D,A7,despesa_funcao!K:K) -> 2361341.1 | C7: =COUNTIF(despesa_funcao!D:D,A:A) -> 13
A8: SECRETARIA DE EDUCAÇÃO E CIDADANIA | B8: =SUMIF(despesa_funcao!D:D,A8,despesa_funcao!K:K) -> 97415942 | C8: =COUNTIF(despesa_funcao!D:D,A:A) -> 88
A9: SECRETARIA DE ESPORTE E QUALIDADE DE VIDA | B9: =SUMIF(despesa_funcao!D:D,A9,despesa_funcao!K:K) -> 5975771.6 | C9: =COUNTIF(despesa_funcao!D:D,A:A) -> 23
A10: SECRETARIA DE APOIO SOCIAL AO CIDADÃO | B10: =SUMIF(despesa_funcao!D:D,A10,despesa_funcao!K:K) -> 8654355 | C10: =COUNTIF(despesa_funcao!D:D,A:A) -> 25
A11: SECRETARIA DE MANUTENÇÃO DA CIDADE | B11: =SUMIF(despesa_funcao!D:D,A11,despesa_funcao!K:K) -> 25107844 | C11: =COUNTIF(despesa_funcao!D:D,A:A) -> 15
A12: SECRETARIA DE SAÚDE | B12: =SUMIF(despesa_funcao!D:D,A12,despesa_funcao!K:K) -> 84243778 | C12: =COUNTIF(despesa_funcao!D:D,A:A) -> 115
A13: SECRETARIA DE MOBILIDADE URBANA | B13: =SUMIF(despesa_funcao!D:D,A13,despesa_funcao!K:K) -> 30679165 | C13: =COUNTIF(despesa_funcao!D:D,A:A) -> 22
... A17: SECRETARIA DE HABITAÇÃO E REGULARIZAÇÃO FUNDIÁRIA | B17: =SUMIF(despesa_funcao!D:D,A17,despesa_funcao!K:K) -> 924217.23 | C17: =COUNTIF(despesa_funcao!D:D,A:A) -> 13
